whr/game.py
whr/player.py
whr/playerday.py
whr/utils.py
whr/whole_history_rating.py
whole_history_rating-1.6.2.dist-info/METADATA
whole_history_rating-1.6.2.dist-info/WHEEL
whole_history_rating-1.6.2.dist-info/top_level.txt
whole_history_rating-1.6.2.dist-info/RECORD
