Metadata-Version: 2.1
Name: whole-history-rating
Version: 1.6.2
Summary: a python convertion from the ruby implementation of Rémi Coulom's Whole-History Rating (WHR) algorithm.
Home-page: https://github.com/pfmonville/whole_history_rating
Author: Pierre-François Monville
Classifier: License :: OSI Approved :: MIT License
Requires-Dist: numpy
